minswap/__init__.py
minswap/addr.py
minswap/assets.py
minswap/models/__init__.py
minswap/models/blockfrost_models.py
minswap/models/common.py
minswap/pools.py
noobminswap-0.0.1.dist-info/LICENSE
noobminswap-0.0.1.dist-info/METADATA
noobminswap-0.0.1.dist-info/WHEEL
noobminswap-0.0.1.dist-info/RECORD
