Metadata-Version: 2.1
Name: noobminswap
Version: 0.0.1
Summary: a temporal minswap-py fork
Home-page: https://github.com/theeldermillenial/minswap-py
License: MIT
Author: noob
Requires-Python: >=3.8.1,<4.0.0
Classifier: License :: OSI Approved :: MIT License
Classifier: Programming Language :: Python :: 3
Classifier: Programming Language :: Python :: 3.9
Classifier: Programming Language :: Python :: 3.10
Classifier: Programming Language :: Python :: 3.11
Requires-Dist: blockfrost-python (==0.5.2)
Requires-Dist: pycardano (==0.7.2)
Requires-Dist: pydantic (==1.10.4)
Requires-Dist: python-dotenv (==0.21.1)
Project-URL: Issues, https://github.com/theeldermillenial/minswap-py/issues
Project-URL: Repository, https://github.com/theeldermillenial/minswap-py
